compreffor/_version.py
compreffor/pyCompressor.py
compreffor/_compreffor.cpython-39-darwin.so
compreffor/__init__.py
compreffor/cxxCompressor.py
compreffor/__main__.py
compreffor/test/pyCompressor_test.py
compreffor/test/util.py
compreffor/test/__init__.py
compreffor/test/dummy.py
compreffor-0.5.6.dist-info/RECORD
compreffor-0.5.6.dist-info/LICENSE
compreffor-0.5.6.dist-info/WHEEL
compreffor-0.5.6.dist-info/entry_points.txt
compreffor-0.5.6.dist-info/top_level.txt
compreffor-0.5.6.dist-info/METADATA
